dlcv/__init__.py
DLCV-0.1.dist-info/METADATA
DLCV-0.1.dist-info/WHEEL
DLCV-0.1.dist-info/entry_points.txt
DLCV-0.1.dist-info/top_level.txt
DLCV-0.1.dist-info/RECORD
