Metadata-Version: 2.1
Name: DLCV
Version: 0.1
Summary: A package for cross-validation of dual leaf models
Author: Prateek Vyas
Author-email: prateek@example.com
Classifier: Programming Language :: Python :: 3
Classifier: License :: OSI Approved :: MIT License
Classifier: Operating System :: OS Independent
Requires-Python: >=3.5
Requires-Dist: numpy
Requires-Dist: scikit-learn
